.hgignore
README
setup.py
vcsdeploy/MainWindow.py
vcsdeploy/MainWindow.ui
vcsdeploy/Ui_MainWindow.py
vcsdeploy/__init__.py
vcsdeploy/autopath.py
vcsdeploy/cmdline.py
vcsdeploy/config.py
vcsdeploy/gitlogic.py
vcsdeploy/hg.py
vcsdeploy/logic.py
vcsdeploy/makefile.py
vcsdeploy/util.py
vcsdeploy/vcsdeploy.pyw
vcsdeploy/vcsdeploy.qrc
vcsdeploy/vcsdeploy_rc.py
vcsdeploy.egg-info/PKG-INFO
vcsdeploy.egg-info/SOURCES.txt
vcsdeploy.egg-info/dependency_links.txt
vcsdeploy.egg-info/requires.txt
vcsdeploy.egg-info/top_level.txt
vcsdeploy/images/view-refresh.png
vcsdeploy/test/__init__.py
vcsdeploy/test/test_logic.py
vcsdeploy/test/test_vcsdeploy.py