Metadata-Version: 1.1
Name: vcsdeploy
Version: 0.5
Summary: Minimal GUI to deploy updates through a VCS repository
Home-page: https://github.com/antocuni/vcsdeploy
Author: Antonio Cuni
Author-email: anto.cuni@gmail.com
License: BSD
Keywords: deployment vcs mercurial GUI
Platform: UNKNOWN
Classifier: Development Status :: 4 - Beta
Classifier: Environment :: X11 Applications :: Qt
Classifier: Environment :: Win32 (MS Windows)
Classifier: License :: OSI Approved :: BSD License
Classifier: Programming Language :: Python
Classifier: Intended Audience :: Developers
Classifier: Operating System :: POSIX
Classifier: Operating System :: Microsoft :: Windows
Classifier: Topic :: System :: Installation/Setup
